isilon_sdk
