Metadata-Version: 2.4
Name: isilon-sdk
Version: 0.7.0
Summary: Python language bindings for managing OneFS clusters.
Home-page: https://github.com/Isilon/isilon_sdk_python
Author: Isilon SDK
Author-email: sdk@isilon.com
Maintainer: Isilon SDK
Maintainer-email: sdk@isilon.com
License: MIT
Project-URL: Source code, https://github.com/Isilon/isilon_sdk
Project-URL: Documentation, https://github.com/Isilon/isilon_sdk_python
Keywords: Swagger,Isilon SDK,OneFS,PowerScale
Classifier: License :: OSI Approved :: MIT License
Classifier: Programming Language :: Python :: 2.7
Classifier: Programming Language :: Python :: 3
Requires-Python: >=2.7
License-File: LICENSE
Requires-Dist: urllib3>=1.15
Requires-Dist: six>=1.10
Requires-Dist: certifi
Requires-Dist: python-dateutil
Dynamic: author
Dynamic: author-email
Dynamic: classifier
Dynamic: description
Dynamic: home-page
Dynamic: keywords
Dynamic: license
Dynamic: license-file
Dynamic: maintainer
Dynamic: maintainer-email
Dynamic: project-url
Dynamic: requires-dist
Dynamic: requires-python
Dynamic: summary
